gfdlws/__init__.py
gfdlws/exchangemessages.py
gfdlws/exchanges.py
gfdlws/exchangesnapshot.py
gfdlws/expirydates.py
gfdlws/history.py
gfdlws/historyaftermarket.py
gfdlws/historygreeks.py
gfdlws/instruments.py
gfdlws/instrumentsonsearch.py
gfdlws/instrumenttypes.py
gfdlws/lastquote.py
gfdlws/lastquotearray.py
gfdlws/lastquotearrayoptiongreeks.py
gfdlws/lastquotearrayshort.py
gfdlws/lastquotearrayshortclose.py
gfdlws/lastquoteoptionchain.py
gfdlws/lastquoteoptiongreeks.py
gfdlws/lastquoteoptiongreekschain.py
gfdlws/lastquoteshort.py
gfdlws/lastquoteshortclose.py
gfdlws/limitation.py
gfdlws/marketmessages.py
gfdlws/optiontypes.py
gfdlws/products.py
gfdlws/quote.py
gfdlws/realsnapshot.py
gfdlws/realtime.py
gfdlws/realtimegreeks.py
gfdlws/serverinfo.py
gfdlws/snapshot.py
gfdlws/strikeprices.py
gfdlws/subscribeoptionchain.py
gfdlws/subscribeoptionchaingreeks.py
gfdlws/subscribetopgainerslosers.py
gfdlws/topgainerslosers.py
gfdlws/ws.py
wsgfdl_py-1.3.4.dist-info/LICENSE
wsgfdl_py-1.3.4.dist-info/METADATA
wsgfdl_py-1.3.4.dist-info/WHEEL
wsgfdl_py-1.3.4.dist-info/top_level.txt
wsgfdl_py-1.3.4.dist-info/RECORD
