Metadata-Version: 2.1
Name: wsgfdl_py
Version: 1.3.4
Summary: Beta Package to implement WebSocket API of Global Datafeeds
Author: Global Datafeeds
Author-email: Global Datafeeds <developer@globaldatafeeds.in>
License: Copyright (c) 2018 The Python Packaging Authority
Classifier: Programming Language :: Python :: 3
Classifier: License :: OSI Approved :: MIT License
Classifier: Operating System :: OS Independent
Requires-Python: >=3.9
License-File: LICENSE
